helloKaraseva/__init__.py
helloKaraseva/fun.py
helloKaraseva-0.1.0.dist-info/METADATA
helloKaraseva-0.1.0.dist-info/WHEEL
helloKaraseva-0.1.0.dist-info/top_level.txt
helloKaraseva-0.1.0.dist-info/RECORD
