Metadata-Version: 2.1
Name: helloKaraseva
Version: 0.1.0
Summary: Lab 2 Python package
Home-page: https://github.com/Karaseva-kote
Author: Karaseva
Author-email: karaseva@niuitmo.ru
License: UNKNOWN
Platform: UNKNOWN
Requires-Dist: numpy (>=1.17.3)
